{
  "nodes": [
    {"id": "action", "name": "Action", "category": "political", "importance": 5},
    {"id": "activism", "name": "Activism", "category": "political", "importance": 3},
    {"id": "alienation", "name": "Alienation", "category": "critical", "importance": 3},
    {"id": "animal-laborans", "name": "Animal Laborans", "category": "human", "importance": 2},
    {"id": "animal-rationale", "name": "Animal Rationale", "category": "human", "importance": 2},
    {"id": "anthropocentrism", "name": "Anthropocentrism", "category": "human", "importance": 2},
    {"id": "beginnings", "name": "Beginnings", "category": "philosophical", "importance": 3},
    {"id": "bourgeois", "name": "Bourgeois", "category": "critical", "importance": 2},
    {"id": "bureaucracy", "name": "Bureaucracy", "category": "critical", "importance": 3},
    {"id": "citizenship", "name": "Citizenship", "category": "political", "importance": 4},
    {"id": "common-good", "name": "Common Good", "category": "political", "importance": 3},
    {"id": "common-interests", "name": "Common Interests", "category": "political", "importance": 2},
    {"id": "common-world", "name": "Common World", "category": "political", "importance": 3},
    {"id": "comprehension", "name": "Comprehension", "category": "philosophical", "importance": 2},
    {"id": "courage", "name": "Courage", "category": "political", "importance": 3},
    {"id": "creativity", "name": "Creativity", "category": "human", "importance": 3},
    {"id": "democracy", "name": "Democracy", "category": "political", "importance": 4},
    {"id": "equality", "name": "Equality", "category": "political", "importance": 3},
    {"id": "evil", "name": "Evil", "category": "critical", "importance": 4},
    {"id": "fabrication", "name": "Fabrication", "category": "human", "importance": 3},
    {"id": "freedom", "name": "Freedom", "category": "political", "importance": 4},
    {"id": "history", "name": "History", "category": "philosophical", "importance": 3},
    {"id": "homo-faber", "name": "Homo Faber", "category": "human", "importance": 2},
    {"id": "human-rights", "name": "Human Rights", "category": "political", "importance": 3},
    {"id": "humanity", "name": "Humanity", "category": "human", "importance": 3},
    {"id": "imagination", "name": "Imagination", "category": "philosophical", "importance": 4},
    {"id": "imperialism", "name": "Imperialism", "category": "critical", "importance": 3},
    {"id": "in-between", "name": "In-between", "category": "political", "importance": 3},
    {"id": "instrumentality", "name": "Instrumentality", "category": "human", "importance": 2},
    {"id": "judgment", "name": "Judgment", "category": "political", "importance": 3},
    {"id": "labor", "name": "Labor", "category": "human", "importance": 4},
    {"id": "law", "name": "Law", "category": "political", "importance": 3},
    {"id": "metabolism", "name": "Metabolism", "category": "human", "importance": 2},
    {"id": "mortality", "name": "Mortality", "category": "human", "importance": 2},
    {"id": "natality", "name": "Natality", "category": "philosophical", "importance": 5},
    {"id": "objectivity", "name": "Objectivity", "category": "philosophical", "importance": 2},
    {"id": "pariah", "name": "Pariah", "category": "political", "importance": 2},
    {"id": "play", "name": "Play", "category": "human", "importance": 2},
    {"id": "plurality", "name": "Plurality", "category": "political", "importance": 5},
    {"id": "power", "name": "Power", "category": "political", "importance": 5},
    {"id": "private-realm", "name": "Private Realm", "category": "political", "importance": 3},
    {"id": "public", "name": "Public", "category": "political", "importance": 5},
    {"id": "reification", "name": "Reification", "category": "critical", "importance": 3},
    {"id": "solitude", "name": "Solitude", "category": "philosophical", "importance": 3},
    {"id": "speech", "name": "Speech", "category": "political", "importance": 4},
    {"id": "spontaneity", "name": "Spontaneity", "category": "human", "importance": 2},
    {"id": "stories", "name": "Stories", "category": "philosophical", "importance": 3},
    {"id": "superfluity", "name": "Superfluity", "category": "critical", "importance": 3},
    {"id": "technology", "name": "Technology", "category": "critical", "importance": 3},
    {"id": "thinking", "name": "Thinking", "category": "philosophical", "importance": 4},
    {"id": "thoughtlessness", "name": "Thoughtlessness", "category": "critical", "importance": 3},
    {"id": "togetherness", "name": "Togetherness", "category": "political", "importance": 3},
    {"id": "totalitarianism", "name": "Totalitarianism", "category": "critical", "importance": 5},
    {"id": "violence", "name": "Violence", "category": "critical", "importance": 4},
    {"id": "vita-activa", "name": "Vita Activa", "category": "human", "importance": 4}
  ],
  "links": [
    {"source": "action", "target": "power"},
    {"source": "action", "target": "public"},
    {"source": "action", "target": "plurality"},
    {"source": "action", "target": "freedom"},
    {"source": "action", "target": "speech"},
    {"source": "action", "target": "natality"},
    {"source": "action", "target": "stories"},
    {"source": "action", "target": "beginnings"},
    {"source": "action", "target": "courage"},
    {"source": "action", "target": "democracy"},
    {"source": "action", "target": "citizenship"},
    {"source": "power", "target": "plurality"},
    {"source": "power", "target": "speech"},
    {"source": "power", "target": "violence"},
    {"source": "power", "target": "public"},
    {"source": "power", "target": "law"},
    {"source": "public", "target": "plurality"},
    {"source": "public", "target": "common-world"},
    {"source": "public", "target": "freedom"},
    {"source": "public", "target": "private-realm"},
    {"source": "public", "target": "togetherness"},
    {"source": "plurality", "target": "equality"},
    {"source": "plurality", "target": "togetherness"},
    {"source": "plurality", "target": "in-between"},
    {"source": "plurality", "target": "humanity"},
    {"source": "freedom", "target": "action"},
    {"source": "freedom", "target": "spontaneity"},
    {"source": "natality", "target": "beginnings"},
    {"source": "natality", "target": "creativity"},
    {"source": "natality", "target": "mortality"},
    {"source": "labor", "target": "animal-laborans"},
    {"source": "labor", "target": "metabolism"},
    {"source": "labor", "target": "work"},
    {"source": "labor", "target": "action"},
    {"source": "work", "target": "homo-faber"},
    {"source": "work", "target": "common-world"},
    {"source": "work", "target": "technology"},
    {"source": "work", "target": "reification"},
    {"source": "work", "target": "creativity"},
    {"source": "work", "target": "action"},
    {"source": "thinking", "target": "judgment"},
    {"source": "thinking", "target": "solitude"},
    {"source": "thinking", "target": "thoughtlessness"},
    {"source": "thinking", "target": "imagination"},
    {"source": "thinking", "target": "evil"},
    {"source": "totalitarianism", "target": "violence"},
    {"source": "totalitarianism", "target": "thoughtlessness"},
    {"source": "totalitarianism", "target": "superfluity"},
    {"source": "totalitarianism", "target": "bureaucracy"},
    {"source": "totalitarianism", "target": "plurality"},
    {"source": "totalitarianism", "target": "power"},
    {"source": "evil", "target": "thoughtlessness"},
    {"source": "evil", "target": "bureaucracy"},
    {"source": "citizenship", "target": "democracy"},
    {"source": "citizenship", "target": "public"},
    {"source": "citizenship", "target": "common-good"},
    {"source": "citizenship", "target": "courage"},
    {"source": "alienation", "target": "common-world"},
    {"source": "alienation", "target": "superfluity"},
    {"source": "imagination", "target": "judgment"},
    {"source": "imagination", "target": "stories"},
    {"source": "history", "target": "stories"},
    {"source": "history", "target": "action"},
    {"source": "humanity", "target": "plurality"},
    {"source": "humanity", "target": "human-rights"},
    {"source": "law", "target": "common-world"},
    {"source": "law", "target": "power"},
    {"source": "technology", "target": "work"},
    {"source": "technology", "target": "alienation"},
    {"source": "violence", "target": "power"},
    {"source": "violence", "target": "work"},
    {"source": "imperialism", "target": "totalitarianism"},
    {"source": "imperialism", "target": "superfluity"},
    {"source": "bureaucracy", "target": "thoughtlessness"},
    {"source": "play", "target": "freedom"},
    {"source": "play", "target": "spontaneity"},
    {"source": "creativity", "target": "natality"},
    {"source": "creativity", "target": "work"},
    {"source": "objectivity", "target": "common-world"},
    {"source": "objectivity", "target": "plurality"},
    {"source": "common-good", "target": "common-world"},
    {"source": "common-good", "target": "public"},
    {"source": "in-between", "target": "public"},
    {"source": "vita-activa", "target": "labor"},
    {"source": "vita-activa", "target": "work"},
    {"source": "vita-activa", "target": "action"},
    {"source": "speech", "target": "plurality"},
    {"source": "speech", "target": "power"},
    {"source": "judgment", "target": "imagination"},
    {"source": "judgment", "target": "thinking"},
    {"source": "stories", "target": "natality"},
    {"source": "stories", "target": "action"},
    {"source": "beginnings", "target": "natality"},
    {"source": "beginnings", "target": "creativity"},
    {"source": "equality", "target": "freedom"},
    {"source": "equality", "target": "democracy"},
    {"source": "democracy", "target": "public"},
    {"source": "democracy", "target": "citizenship"},
    {"source": "courage", "target": "action"},
    {"source": "courage", "target": "citizenship"}
  ]
}
